{
  "collectionName": "components_section_hero_sections",
  "info": {
    "displayName": "Hero section",
    "icon": "dashboard"
  },
  "options": {},
  "attributes": {
    "title": {
      "type": "string"
    },
    "description": {
      "type": "text"
    },
    "backgroundImage": {
      "allowedTypes": [
        "images",
        "files",
        "videos",
        "audios"
      ],
      "type": "media",
      "multiple": false
    },
    "callToAction": {
      "displayName": "Call To Action",
      "type": "component",
      "repeatable": false,
      "component": "element.call-to-action"
    }
  }
}
